dl_interface/__init__.py
dl_interface/models.py
dl_interface/request.py
promsoft_dl_interface-0.1.21.dist-info/METADATA
promsoft_dl_interface-0.1.21.dist-info/WHEEL
promsoft_dl_interface-0.1.21.dist-info/RECORD
