Metadata-Version: 2.1
Name: promsoft_dl_interface
Version: 0.1.21
Summary: Интерфейс HTTP API транспортной компании Деловые линии.
Author: Promsoft
Author-email: info@promsoft.ru
Requires-Python: >=3.10,<4.0
Classifier: Programming Language :: Python :: 3
Classifier: Programming Language :: Python :: 3.10
Classifier: Programming Language :: Python :: 3.11
Classifier: Programming Language :: Python :: 3.12
Requires-Dist: pydantic (>=1.10.7,<2.0.0)
